brawlstars_api/__init__.py
brawlstars_api/api_client.py
brawlstars_api/configuration.py
brawlstars_api/rest.py
brawlstars_api/api/__init__.py
brawlstars_api/api/brawlers_api.py
brawlstars_api/api/clubs_api.py
brawlstars_api/api/players_api.py
brawlstars_api/api/rankings_api.py
brawlstars_api/models/__init__.py
brawlstars_api/models/battle.py
brawlstars_api/models/battle_list.py
brawlstars_api/models/battle_result.py
brawlstars_api/models/brawler.py
brawlstars_api/models/brawler_list.py
brawlstars_api/models/brawler_stat.py
brawlstars_api/models/brawler_stat_list.py
brawlstars_api/models/client_error.py
brawlstars_api/models/club.py
brawlstars_api/models/club_member.py
brawlstars_api/models/club_member_list.py
brawlstars_api/models/club_ranking.py
brawlstars_api/models/club_ranking_list.py
brawlstars_api/models/event.py
brawlstars_api/models/json_localized_name.py
brawlstars_api/models/player.py
brawlstars_api/models/player_club.py
brawlstars_api/models/player_ranking.py
brawlstars_api/models/player_ranking_club.py
brawlstars_api/models/player_ranking_list.py
brawlstars_api/models/star_power.py
brawlstars_api/models/star_power_list.py
test/__init__.py
test/test_battle.py
test/test_battle_list.py
test/test_battle_result.py
test/test_brawler.py
test/test_brawler_list.py
test/test_brawler_stat.py
test/test_brawler_stat_list.py
test/test_brawlers_api.py
test/test_client_error.py
test/test_club.py
test/test_club_member.py
test/test_club_member_list.py
test/test_club_ranking.py
test/test_club_ranking_list.py
test/test_clubs_api.py
test/test_event.py
test/test_json_localized_name.py
test/test_player.py
test/test_player_club.py
test/test_player_ranking.py
test/test_player_ranking_club.py
test/test_player_ranking_list.py
test/test_players_api.py
test/test_rankings_api.py
test/test_star_power.py
test/test_star_power_list.py
brawlstars_api-1.2.0.dist-info/METADATA
brawlstars_api-1.2.0.dist-info/WHEEL
brawlstars_api-1.2.0.dist-info/top_level.txt
brawlstars_api-1.2.0.dist-info/RECORD
